adpwebscrape/__init__.py
adpwebscrape/adp_resource.py
adp_webscrape-0.1.0.dist-info/LICENSE
adp_webscrape-0.1.0.dist-info/WHEEL
adp_webscrape-0.1.0.dist-info/METADATA
adp_webscrape-0.1.0.dist-info/RECORD
